time_series_model_basics/None.py
time_series_model_basics/__init__.py
time_series_model_basics/_nbdev.py
time_series_model_basics/index.py
time_series_model_basics/interactive.py
time_series_model_basics/metrics.py
time_series_model_basics/moving_average.py
time_series_model_basics/optimizers.py
time_series_model_basics/simulate_data.py
time_series_model_basics/smoothing.py
time_series_model_basics-0.0.5.dist-info/LICENSE
time_series_model_basics-0.0.5.dist-info/METADATA
time_series_model_basics-0.0.5.dist-info/WHEEL
time_series_model_basics-0.0.5.dist-info/entry_points.txt
time_series_model_basics-0.0.5.dist-info/top_level.txt
time_series_model_basics-0.0.5.dist-info/RECORD
