Metadata-Version: 2.1
Name: time-series-model-basics
Version: 0.0.5
Summary: Put a description
Home-page: https://github.com/kikejimenez/time_series_model_basics/tree/master/
Author: Enrique Jimenez
Author-email: physieira@gmail.com
License: Apache Software License 2.0
Keywords: data analytics forecasting
Platform: UNKNOWN
Classifier: Development Status :: 3 - Alpha
Classifier: Intended Audience :: Developers
Classifier: Natural Language :: English
Classifier: Programming Language :: Python :: 3.6
Classifier: Programming Language :: Python :: 3.7
Classifier: Programming Language :: Python :: 3.8
Classifier: License :: OSI Approved :: Apache Software License
Requires-Python: >=3.6
Requires-Dist: pip
Requires-Dist: packaging
Requires-Dist: numpy
Requires-Dist: pandas
Requires-Dist: scipy
Requires-Dist: numba
Requires-Dist: matplotlib
Requires-Dist: plotly
Requires-Dist: sklearn
Requires-Dist: kaleido
Requires-Dist: scikit-optimize
Requires-Dist: statsmodels
Provides-Extra: dev
